clara/viz/core/VERSION
clara/viz/core/__init__.py
clara/viz/core/_version.py
clara/viz/core/_viz.cpython-310-x86_64-linux-gnu.so
clara/viz/core/_viz.cpython-311-x86_64-linux-gnu.so
clara/viz/core/_viz.cpython-312-x86_64-linux-gnu.so
clara/viz/core/_viz.cpython-39-x86_64-linux-gnu.so
clara/viz/core/datadefinition.py
clara/viz/core/importutil.py
clara_viz_core.libs/libclara_viz_renderer-c791442a.so.0.4.2
clara_viz_core.libs/libcuda-98b825dd.so.550.163.01
clara_viz_core-0.4.2.dist-info/METADATA
clara_viz_core-0.4.2.dist-info/WHEEL
clara_viz_core-0.4.2.dist-info/top_level.txt
clara_viz_core-0.4.2.dist-info/RECORD
clara_viz_core-0.4.2.dist-info/licenses/LICENSE
