Metadata-Version: 2.4
Name: clara-viz-core
Version: 0.4.2
Summary: A toolkit to provide GPU accelerated visualization of medical data.
Home-page: https://github.com/NVIDIA/clara-viz
Author: NVIDIA Corporation
License: Apache-2.0
Platform: manylinux_2_28_x86_64
Classifier: Development Status :: 4 - Beta
Classifier: Intended Audience :: Developers
Classifier: Intended Audience :: Science/Research
Classifier: Topic :: Multimedia :: Graphics
Classifier: Programming Language :: Python :: 3
Classifier: Programming Language :: Python :: 3.9
Classifier: Programming Language :: Python :: 3.10
Classifier: Programming Language :: Python :: 3.11
Classifier: Programming Language :: Python :: 3.12
Requires-Python: >= 3.9, < 3.13
License-File: LICENSE
Requires-Dist: packaging
Provides-Extra: all
Requires-Dist: numpy; extra == "all"
Requires-Dist: itk-io>=5.2; extra == "all"
Requires-Dist: itk-filtering>=5.2; extra == "all"
Requires-Dist: cucim>=22.02.00; extra == "all"
Provides-Extra: numpy
Requires-Dist: numpy; extra == "numpy"
Provides-Extra: itk
Requires-Dist: itk-io>=5.2; extra == "itk"
Requires-Dist: itk-filtering>=5.2; extra == "itk"
Provides-Extra: cucim
Requires-Dist: cucim>=22.02.00; extra == "cucim"
Dynamic: author
Dynamic: classifier
Dynamic: description
Dynamic: description-content-type
Dynamic: home-page
Dynamic: license
Dynamic: license-file
Dynamic: platform
Dynamic: requires-dist
Dynamic: requires-python
Dynamic: summary
